design.sv
module seqdetector(in,clk,out);
  input in,clk;
  output reg out;
  parameter s0=0,s1=1,s2=2,s3=3;
  reg [1:0]state;
  always @ (posedge clk)
    begin
      case(state)
        s0:begin
          if(!in)
            begin
              state<=s1;
              out<=1'b0;
            end
          else
            begin
              state<=s0;
              out<=1'b0;
            end
        end
        s1:begin
          if(!in)
            begin
              state<=s1;
              out<=1'b0;
            end
          else
            begin
              state<=s2;
              out<=1'b0;
            end
        end
        s2:begin
          if(!in)
            begin
              state<=s1;
              out<=1'b0;
            end
          else
            begin
              state<=s3;
              out<=1'b0;
            end
        end
        s3:begin
          if(!in)
            begin
              state<=s1;
              out<=1'b1;
            end
          else
            begin
              state<=s0;
              out<=1'b0;
            end
        end
        default:
          begin
          if(!in)
            begin
              state<=s1;
              out<=1'b0;
            end
          else
            begin
              state<=s0;
              out<=1'b0;
            end
        end
      endcase
    end
endmodule

testbench.sv
module tb;
  reg in,clk;
  wire out;
  seqdetector sd0(in,clk,out);
  always #5 clk=~clk;
  initial
    begin
      clk=1'b0;
      #5
      in=1'b0;
      #10
      in=1'b1;
      #10
      in=1'b1;
      #10
      in=1'b0;
      #10
      in=1'b1;
      #10
      in=1'b1;
      #10
      in=1'b0;
      #5 $finish;
    end
   initial
     begin
       $dumpfile("seqdetector.vcd");
       $dumpvars(0,tb);
       $monitor($time," in=%b out=%b ",in,out);
     end
      endmodule

seqdetector.vcd
$date
	Wed Sep 13 13:34:59 2023
$end
$version
	Icarus Verilog
$end
$timescale
	1s
$end
$scope module tb $end
$var wire 1 ! out $end
$var reg 1 " clk $end
$var reg 1 # in $end
$scope module sd0 $end
$var wire 1 $ clk $end
$var wire 1 % in $end
$var reg 1 & out $end
$var reg 2 ' state [1:0] $end
$upscope $end
$upscope $end
$enddefinitions $end
#0
$dumpvars
bx '
x&
x%
0$
x#
0"
x!
$end
#5
0&
0!
b1 '
0#
0%
1"
1$
#10
0"
0$
#15
b10 '
1"
1$
1#
1%
#20
0"
0$
#25
b11 '
1"
1$
#30
0"
0$
#35
1&
1!
b1 '
1"
1$
0#
0%
#40
0"
0$
#45
0&
0!
b10 '
1"
1$
1#
1%
#50
0"
0$
#55
b11 '
1"
1$
#60
0"
0$
#65
1&
1!
b1 '
1"
1$
0#
0%
